rossendorfer_farbenliste/Gradients.png
rossendorfer_farbenliste/__init__.py
rossendorfer_farbenliste-1.0.4.dist-info/LICENSE
rossendorfer_farbenliste-1.0.4.dist-info/METADATA
rossendorfer_farbenliste-1.0.4.dist-info/WHEEL
rossendorfer_farbenliste-1.0.4.dist-info/top_level.txt
rossendorfer_farbenliste-1.0.4.dist-info/RECORD
