Metadata-Version: 2.1
Name: rossendorfer_farbenliste
Version: 1.0.4
Summary: Definition of some colors and colorscales
Home-page: UNKNOWN
Author: Michal Smid
Author-email: m.smid@hzdr.de
License: UNKNOWN
Platform: UNKNOWN
Classifier: Programming Language :: Python :: 3
Classifier: License :: OSI Approved :: MIT License
Classifier: Operating System :: OS Independent
Requires-Python: >=3.6
License-File: LICENSE
